dipwmsearch/AhoCorasick.py
dipwmsearch/Block.py
dipwmsearch/Enumerate.py
dipwmsearch/SemiNaive.py
dipwmsearch/__init__.py
dipwmsearch/__main__.py
dipwmsearch/diPwm.py
dipwmsearch-0.1.8.dist-info/LICENSE.txt
dipwmsearch-0.1.8.dist-info/METADATA
dipwmsearch-0.1.8.dist-info/WHEEL
dipwmsearch-0.1.8.dist-info/top_level.txt
dipwmsearch-0.1.8.dist-info/RECORD
