Metadata-Version: 2.1
Name: dipwmsearch
Version: 0.1.8
Summary: Provides functions to search for any di-nucleotidic Position Weight Matrix (di-PWM) in a genomic sequence (IUPAC compliant).
Author-email: Marie Mille <m.mariemille@gmail.com>, Bastien Cazaux <bast.cazaux@gmail.com>, Julie Ripoll <julie.ripoll@lirmm.fr>, Eric Rivals <rivals@lirmm.fr>
License: A package dedicated to search for diPWM motifs in a sequence or a text. Copyright CNRS 2021-; by Marie Mille, Bastien Cazaux, Julie Ripoll and Eric Rivals.
Project-URL: Homepage, https://gite.lirmm.fr/rivals/dipwmsearch
Project-URL: Documentation, https://rivals.lirmm.net/dipwmsearch/
Keywords: bioinformatics,motif,binding site,transcription,transcription factor,biology,genomics,PWM,Position Weight Matrix,dinucleotide,dinucleotidic,IUPAC
Classifier: Programming Language :: Python :: 3
Classifier: License :: CeCILL-B Free Software License Agreement (CECILL-B)
Requires-Python: >=3.8
License-File: LICENSE.txt
Requires-Dist: pyahocorasick
Requires-Dist: pytest
Requires-Dist: pandas
Requires-Dist: biopython
